AnsiLib/AnsiLib.py
AnsiLib/__init__.py
AnsiLib/chars.py
AnsiLib/color.py
AnsiLib/utils.py
ansilib-1.1.0.dist-info/licenses/LICENSE.txt
ansilib-1.1.0.dist-info/METADATA
ansilib-1.1.0.dist-info/WHEEL
ansilib-1.1.0.dist-info/top_level.txt
ansilib-1.1.0.dist-info/RECORD
