Metadata-Version: 2.4
Name: AnsiLib
Version: 1.1.0
Summary: A library for handling ANSI codes
Home-page: https://github.com/boraboyacioglu-itu/ansilib
Author: Bora Boyacıoğlu
Author-email: boyacioglu20@itu.edu.tr
License: MIT License
Classifier: Programming Language :: Python :: 3
Classifier: License :: OSI Approved :: MIT License
Classifier: Operating System :: OS Independent
Requires-Python: >=3.5
License-File: LICENSE.txt
Dynamic: author
Dynamic: author-email
Dynamic: classifier
Dynamic: description
Dynamic: description-content-type
Dynamic: home-page
Dynamic: license
Dynamic: license-file
Dynamic: requires-python
Dynamic: summary
